{
  "hawks_nest": {
    "name": "Hawks Nest",
    "region": "Port Stephens",
    "updatedAt": "2026-02-08T06:49:49.682Z",
    "current": {
      "score": 3,
      "recommendation": "MAYBE",
      "bestTimes": [
        "Dawn",
        "Dusk"
      ],
      "species": [
        "Tailor",
        "Flathead",
        "Bream"
      ],
      "wind": {
        "speed": 11,
        "direction": "NE",
        "degrees": 40,
        "max": 18
      },
      "swell": {
        "height": null
      },
      "tide": {
        "state": "Run-in (approx)",
        "next": "Best bite ±2 hrs around tide change (approx)"
      }
    },
    "daily": [
      {
        "date": "2026-02-08",
        "score": 3,
        "recommendation": "MAYBE",
        "wind": {
          "max": 18,
          "direction": "NE",
          "degrees": 59
        },
        "swell": {
          "max": null
        },
        "tideState": "Run-in (approx)",
        "speciesTop": [
          "Tailor",
          "Flathead",
          "Bream"
        ]
      },
      {
        "date": "2026-02-09",
        "score": 2,
        "recommendation": "GO TO PUB",
        "wind": {
          "max": 19,
          "direction": "NE",
          "degrees": 29
        },
        "swell": {
          "max": null
        },
        "tideState": "Run-out (approx)",
        "speciesTop": [
          "Tailor",
          "Flathead",
          "Bream"
        ]
      },
      {
        "date": "2026-02-10",
        "score": 3,
        "recommendation": "MAYBE",
        "wind": {
          "max": 13,
          "direction": "S",
          "degrees": 188
        },
        "swell": {
          "max": null
        },
        "tideState": "Run-in (approx)",
        "speciesTop": [
          "Tailor",
          "Flathead",
          "Bream"
        ]
      },
      {
        "date": "2026-02-11",
        "score": 3,
        "recommendation": "MAYBE",
        "wind": {
          "max": 15,
          "direction": "NE",
          "degrees": 52
        },
        "swell": {
          "max": null
        },
        "tideState": "Run-out (approx)",
        "speciesTop": [
          "Tailor",
          "Flathead",
          "Bream"
        ]
      },
      {
        "date": "2026-02-12",
        "score": 2,
        "recommendation": "GO TO PUB",
        "wind": {
          "max": 24,
          "direction": "S",
          "degrees": 182
        },
        "swell": {
          "max": null
        },
        "tideState": "Run-in (approx)",
        "speciesTop": [
          "Tailor",
          "Flathead",
          "Bream"
        ]
      },
      {
        "date": "2026-02-13",
        "score": 3,
        "recommendation": "MAYBE",
        "wind": {
          "max": 18,
          "direction": "SE",
          "degrees": 122
        },
        "swell": {
          "max": null
        },
        "tideState": "Run-out (approx)",
        "speciesTop": [
          "Tailor",
          "Flathead",
          "Bream"
        ]
      },
      {
        "date": "2026-02-14",
        "score": 3,
        "recommendation": "MAYBE",
        "wind": {
          "max": 15,
          "direction": "E",
          "degrees": 89
        },
        "swell": {
          "max": null
        },
        "tideState": "Run-in (approx)",
        "speciesTop": [
          "Tailor",
          "Flathead",
          "Bream"
        ]
      }
    ]
  },
  "fingal_bay": {
    "name": "Fingal Bay",
    "region": "Port Stephens",
    "updatedAt": "2026-02-08T06:49:49.682Z",
    "current": {
      "score": 2,
      "recommendation": "GO TO PUB",
      "bestTimes": [
        "Dawn",
        "Dusk"
      ],
      "species": [
        "Tailor",
        "Flathead",
        "Bream"
      ],
      "wind": {
        "speed": 16,
        "direction": "NE",
        "degrees": 36,
        "max": 21
      },
      "swell": {
        "height": null
      },
      "tide": {
        "state": "Run-in (approx)",
        "next": "Best bite ±2 hrs around tide change (approx)"
      }
    },
    "daily": [
      {
        "date": "2026-02-08",
        "score": 2,
        "recommendation": "GO TO PUB",
        "wind": {
          "max": 21,
          "direction": "NE",
          "degrees": 59
        },
        "swell": {
          "max": null
        },
        "tideState": "Run-in (approx)",
        "speciesTop": [
          "Tailor",
          "Flathead",
          "Bream"
        ]
      },
      {
        "date": "2026-02-09",
        "score": 1,
        "recommendation": "GO TO PUB",
        "wind": {
          "max": 25,
          "direction": "NE",
          "degrees": 23
        },
        "swell": {
          "max": null
        },
        "tideState": "Run-out (approx)",
        "speciesTop": [
          "Tailor",
          "Flathead",
          "Bream"
        ]
      },
      {
        "date": "2026-02-10",
        "score": 3,
        "recommendation": "MAYBE",
        "wind": {
          "max": 13,
          "direction": "S",
          "degrees": 201
        },
        "swell": {
          "max": null
        },
        "tideState": "Run-in (approx)",
        "speciesTop": [
          "Tailor",
          "Flathead",
          "Bream"
        ]
      },
      {
        "date": "2026-02-11",
        "score": 2,
        "recommendation": "GO TO PUB",
        "wind": {
          "max": 19,
          "direction": "NE",
          "degrees": 46
        },
        "swell": {
          "max": null
        },
        "tideState": "Run-out (approx)",
        "speciesTop": [
          "Tailor",
          "Flathead",
          "Bream"
        ]
      },
      {
        "date": "2026-02-12",
        "score": 1,
        "recommendation": "GO TO PUB",
        "wind": {
          "max": 34,
          "direction": "S",
          "degrees": 166
        },
        "swell": {
          "max": null
        },
        "tideState": "Run-in (approx)",
        "speciesTop": [
          "Tailor",
          "Flathead",
          "Bream"
        ]
      },
      {
        "date": "2026-02-13",
        "score": 1,
        "recommendation": "GO TO PUB",
        "wind": {
          "max": 25,
          "direction": "SE",
          "degrees": 124
        },
        "swell": {
          "max": null
        },
        "tideState": "Run-out (approx)",
        "speciesTop": [
          "Tailor",
          "Flathead",
          "Bream"
        ]
      },
      {
        "date": "2026-02-14",
        "score": 3,
        "recommendation": "MAYBE",
        "wind": {
          "max": 18,
          "direction": "E",
          "degrees": 85
        },
        "swell": {
          "max": null
        },
        "tideState": "Run-in (approx)",
        "speciesTop": [
          "Tailor",
          "Flathead",
          "Bream"
        ]
      }
    ]
  },
  "nelson_bay": {
    "name": "Nelson Bay",
    "region": "Port Stephens",
    "updatedAt": "2026-02-08T06:49:49.682Z",
    "current": {
      "score": 2,
      "recommendation": "GO TO PUB",
      "bestTimes": [
        "Dawn",
        "Dusk"
      ],
      "species": [
        "Tailor",
        "Flathead",
        "Bream"
      ],
      "wind": {
        "speed": 16,
        "direction": "NE",
        "degrees": 36,
        "max": 21
      },
      "swell": {
        "height": null
      },
      "tide": {
        "state": "Run-in (approx)",
        "next": "Best bite ±2 hrs around tide change (approx)"
      }
    },
    "daily": [
      {
        "date": "2026-02-08",
        "score": 2,
        "recommendation": "GO TO PUB",
        "wind": {
          "max": 21,
          "direction": "NE",
          "degrees": 59
        },
        "swell": {
          "max": null
        },
        "tideState": "Run-in (approx)",
        "speciesTop": [
          "Tailor",
          "Flathead",
          "Bream"
        ]
      },
      {
        "date": "2026-02-09",
        "score": 1,
        "recommendation": "GO TO PUB",
        "wind": {
          "max": 25,
          "direction": "NE",
          "degrees": 23
        },
        "swell": {
          "max": null
        },
        "tideState": "Run-out (approx)",
        "speciesTop": [
          "Tailor",
          "Flathead",
          "Bream"
        ]
      },
      {
        "date": "2026-02-10",
        "score": 3,
        "recommendation": "MAYBE",
        "wind": {
          "max": 13,
          "direction": "S",
          "degrees": 201
        },
        "swell": {
          "max": null
        },
        "tideState": "Run-in (approx)",
        "speciesTop": [
          "Tailor",
          "Flathead",
          "Bream"
        ]
      },
      {
        "date": "2026-02-11",
        "score": 2,
        "recommendation": "GO TO PUB",
        "wind": {
          "max": 19,
          "direction": "NE",
          "degrees": 46
        },
        "swell": {
          "max": null
        },
        "tideState": "Run-out (approx)",
        "speciesTop": [
          "Tailor",
          "Flathead",
          "Bream"
        ]
      },
      {
        "date": "2026-02-12",
        "score": 1,
        "recommendation": "GO TO PUB",
        "wind": {
          "max": 34,
          "direction": "S",
          "degrees": 166
        },
        "swell": {
          "max": null
        },
        "tideState": "Run-in (approx)",
        "speciesTop": [
          "Tailor",
          "Flathead",
          "Bream"
        ]
      },
      {
        "date": "2026-02-13",
        "score": 1,
        "recommendation": "GO TO PUB",
        "wind": {
          "max": 25,
          "direction": "SE",
          "degrees": 124
        },
        "swell": {
          "max": null
        },
        "tideState": "Run-out (approx)",
        "speciesTop": [
          "Tailor",
          "Flathead",
          "Bream"
        ]
      },
      {
        "date": "2026-02-14",
        "score": 3,
        "recommendation": "MAYBE",
        "wind": {
          "max": 18,
          "direction": "E",
          "degrees": 85
        },
        "swell": {
          "max": null
        },
        "tideState": "Run-in (approx)",
        "speciesTop": [
          "Tailor",
          "Flathead",
          "Bream"
        ]
      }
    ]
  },
  "newcastle_beach": {
    "name": "Newcastle Beach",
    "region": "Newcastle",
    "updatedAt": "2026-02-08T06:49:49.682Z",
    "current": {
      "score": 3,
      "recommendation": "MAYBE",
      "bestTimes": [
        "Dawn",
        "Dusk"
      ],
      "species": [
        "Tailor",
        "Flathead",
        "Bream"
      ],
      "wind": {
        "speed": 4,
        "direction": "SE",
        "degrees": 156,
        "max": 14
      },
      "swell": {
        "height": null
      },
      "tide": {
        "state": "Run-in (approx)",
        "next": "Best bite ±2 hrs around tide change (approx)"
      }
    },
    "daily": [
      {
        "date": "2026-02-08",
        "score": 3,
        "recommendation": "MAYBE",
        "wind": {
          "max": 14,
          "direction": "SE",
          "degrees": 146
        },
        "swell": {
          "max": null
        },
        "tideState": "Run-in (approx)",
        "speciesTop": [
          "Tailor",
          "Flathead",
          "Bream"
        ]
      },
      {
        "date": "2026-02-09",
        "score": 3,
        "recommendation": "MAYBE",
        "wind": {
          "max": 12,
          "direction": "N",
          "degrees": 8
        },
        "swell": {
          "max": null
        },
        "tideState": "Run-out (approx)",
        "speciesTop": [
          "Tailor",
          "Bream",
          "Flathead"
        ]
      },
      {
        "date": "2026-02-10",
        "score": 4,
        "recommendation": "SEND IT",
        "wind": {
          "max": 12,
          "direction": "SE",
          "degrees": 157
        },
        "swell": {
          "max": null
        },
        "tideState": "Run-in (approx)",
        "speciesTop": [
          "Tailor",
          "Bream",
          "Flathead"
        ]
      },
      {
        "date": "2026-02-11",
        "score": 4,
        "recommendation": "SEND IT",
        "wind": {
          "max": 11,
          "direction": "NE",
          "degrees": 40
        },
        "swell": {
          "max": null
        },
        "tideState": "Run-out (approx)",
        "speciesTop": [
          "Tailor",
          "Bream",
          "Flathead"
        ]
      },
      {
        "date": "2026-02-12",
        "score": 2,
        "recommendation": "GO TO PUB",
        "wind": {
          "max": 24,
          "direction": "S",
          "degrees": 190
        },
        "swell": {
          "max": null
        },
        "tideState": "Run-in (approx)",
        "speciesTop": [
          "Tailor",
          "Flathead",
          "Bream"
        ]
      },
      {
        "date": "2026-02-13",
        "score": 3,
        "recommendation": "MAYBE",
        "wind": {
          "max": 17,
          "direction": "SE",
          "degrees": 124
        },
        "swell": {
          "max": null
        },
        "tideState": "Run-out (approx)",
        "speciesTop": [
          "Tailor",
          "Flathead",
          "Bream"
        ]
      },
      {
        "date": "2026-02-14",
        "score": 3,
        "recommendation": "MAYBE",
        "wind": {
          "max": 14,
          "direction": "E",
          "degrees": 92
        },
        "swell": {
          "max": null
        },
        "tideState": "Run-in (approx)",
        "speciesTop": [
          "Tailor",
          "Flathead",
          "Bream"
        ]
      }
    ]
  },
  "merewether": {
    "name": "Merewether",
    "region": "Newcastle",
    "updatedAt": "2026-02-08T06:49:49.682Z",
    "current": {
      "score": 3,
      "recommendation": "MAYBE",
      "bestTimes": [
        "Dawn",
        "Dusk"
      ],
      "species": [
        "Tailor",
        "Flathead",
        "Bream"
      ],
      "wind": {
        "speed": 4,
        "direction": "SE",
        "degrees": 143,
        "max": 18
      },
      "swell": {
        "height": null
      },
      "tide": {
        "state": "Run-in (approx)",
        "next": "Best bite ±2 hrs around tide change (approx)"
      }
    },
    "daily": [
      {
        "date": "2026-02-08",
        "score": 3,
        "recommendation": "MAYBE",
        "wind": {
          "max": 18,
          "direction": "S",
          "degrees": 169
        },
        "swell": {
          "max": null
        },
        "tideState": "Run-in (approx)",
        "speciesTop": [
          "Tailor",
          "Flathead",
          "Bream"
        ]
      },
      {
        "date": "2026-02-09",
        "score": 3,
        "recommendation": "MAYBE",
        "wind": {
          "max": 14,
          "direction": "N",
          "degrees": 5
        },
        "swell": {
          "max": null
        },
        "tideState": "Run-out (approx)",
        "speciesTop": [
          "Tailor",
          "Flathead",
          "Bream"
        ]
      },
      {
        "date": "2026-02-10",
        "score": 3,
        "recommendation": "MAYBE",
        "wind": {
          "max": 13,
          "direction": "SE",
          "degrees": 150
        },
        "swell": {
          "max": null
        },
        "tideState": "Run-in (approx)",
        "speciesTop": [
          "Tailor",
          "Flathead",
          "Bream"
        ]
      },
      {
        "date": "2026-02-11",
        "score": 3,
        "recommendation": "MAYBE",
        "wind": {
          "max": 16,
          "direction": "NE",
          "degrees": 33
        },
        "swell": {
          "max": null
        },
        "tideState": "Run-out (approx)",
        "speciesTop": [
          "Tailor",
          "Flathead",
          "Bream"
        ]
      },
      {
        "date": "2026-02-12",
        "score": 1,
        "recommendation": "GO TO PUB",
        "wind": {
          "max": 27,
          "direction": "S",
          "degrees": 176
        },
        "swell": {
          "max": null
        },
        "tideState": "Run-in (approx)",
        "speciesTop": [
          "Tailor",
          "Flathead",
          "Bream"
        ]
      },
      {
        "date": "2026-02-13",
        "score": 2,
        "recommendation": "GO TO PUB",
        "wind": {
          "max": 23,
          "direction": "SE",
          "degrees": 126
        },
        "swell": {
          "max": null
        },
        "tideState": "Run-out (approx)",
        "speciesTop": [
          "Tailor",
          "Flathead",
          "Bream"
        ]
      },
      {
        "date": "2026-02-14",
        "score": 3,
        "recommendation": "MAYBE",
        "wind": {
          "max": 17,
          "direction": "E",
          "degrees": 81
        },
        "swell": {
          "max": null
        },
        "tideState": "Run-in (approx)",
        "speciesTop": [
          "Tailor",
          "Flathead",
          "Bream"
        ]
      }
    ]
  },
  "swansea": {
    "name": "Swansea",
    "region": "Lake Macquarie",
    "updatedAt": "2026-02-08T06:49:49.682Z",
    "current": {
      "score": 3,
      "recommendation": "MAYBE",
      "bestTimes": [
        "Dawn",
        "Dusk"
      ],
      "species": [
        "Tailor",
        "Flathead",
        "Bream"
      ],
      "wind": {
        "speed": 4,
        "direction": "SE",
        "degrees": 143,
        "max": 18
      },
      "swell": {
        "height": null
      },
      "tide": {
        "state": "Run-in (approx)",
        "next": "Best bite ±2 hrs around tide change (approx)"
      }
    },
    "daily": [
      {
        "date": "2026-02-08",
        "score": 3,
        "recommendation": "MAYBE",
        "wind": {
          "max": 18,
          "direction": "S",
          "degrees": 169
        },
        "swell": {
          "max": null
        },
        "tideState": "Run-in (approx)",
        "speciesTop": [
          "Tailor",
          "Flathead",
          "Bream"
        ]
      },
      {
        "date": "2026-02-09",
        "score": 3,
        "recommendation": "MAYBE",
        "wind": {
          "max": 14,
          "direction": "N",
          "degrees": 5
        },
        "swell": {
          "max": null
        },
        "tideState": "Run-out (approx)",
        "speciesTop": [
          "Tailor",
          "Flathead",
          "Bream"
        ]
      },
      {
        "date": "2026-02-10",
        "score": 3,
        "recommendation": "MAYBE",
        "wind": {
          "max": 13,
          "direction": "SE",
          "degrees": 150
        },
        "swell": {
          "max": null
        },
        "tideState": "Run-in (approx)",
        "speciesTop": [
          "Tailor",
          "Flathead",
          "Bream"
        ]
      },
      {
        "date": "2026-02-11",
        "score": 3,
        "recommendation": "MAYBE",
        "wind": {
          "max": 16,
          "direction": "NE",
          "degrees": 33
        },
        "swell": {
          "max": null
        },
        "tideState": "Run-out (approx)",
        "speciesTop": [
          "Tailor",
          "Flathead",
          "Bream"
        ]
      },
      {
        "date": "2026-02-12",
        "score": 1,
        "recommendation": "GO TO PUB",
        "wind": {
          "max": 27,
          "direction": "S",
          "degrees": 176
        },
        "swell": {
          "max": null
        },
        "tideState": "Run-in (approx)",
        "speciesTop": [
          "Tailor",
          "Flathead",
          "Bream"
        ]
      },
      {
        "date": "2026-02-13",
        "score": 2,
        "recommendation": "GO TO PUB",
        "wind": {
          "max": 23,
          "direction": "SE",
          "degrees": 126
        },
        "swell": {
          "max": null
        },
        "tideState": "Run-out (approx)",
        "speciesTop": [
          "Tailor",
          "Flathead",
          "Bream"
        ]
      },
      {
        "date": "2026-02-14",
        "score": 3,
        "recommendation": "MAYBE",
        "wind": {
          "max": 17,
          "direction": "E",
          "degrees": 81
        },
        "swell": {
          "max": null
        },
        "tideState": "Run-in (approx)",
        "speciesTop": [
          "Tailor",
          "Flathead",
          "Bream"
        ]
      }
    ]
  },
  "caves_beach": {
    "name": "Caves Beach",
    "region": "Lake Macquarie",
    "updatedAt": "2026-02-08T06:49:49.682Z",
    "current": {
      "score": 3,
      "recommendation": "MAYBE",
      "bestTimes": [
        "Dawn",
        "Dusk"
      ],
      "species": [
        "Tailor",
        "Flathead",
        "Bream"
      ],
      "wind": {
        "speed": 4,
        "direction": "SE",
        "degrees": 143,
        "max": 18
      },
      "swell": {
        "height": null
      },
      "tide": {
        "state": "Run-in (approx)",
        "next": "Best bite ±2 hrs around tide change (approx)"
      }
    },
    "daily": [
      {
        "date": "2026-02-08",
        "score": 3,
        "recommendation": "MAYBE",
        "wind": {
          "max": 18,
          "direction": "S",
          "degrees": 169
        },
        "swell": {
          "max": null
        },
        "tideState": "Run-in (approx)",
        "speciesTop": [
          "Tailor",
          "Flathead",
          "Bream"
        ]
      },
      {
        "date": "2026-02-09",
        "score": 3,
        "recommendation": "MAYBE",
        "wind": {
          "max": 14,
          "direction": "N",
          "degrees": 5
        },
        "swell": {
          "max": null
        },
        "tideState": "Run-out (approx)",
        "speciesTop": [
          "Tailor",
          "Flathead",
          "Bream"
        ]
      },
      {
        "date": "2026-02-10",
        "score": 3,
        "recommendation": "MAYBE",
        "wind": {
          "max": 13,
          "direction": "SE",
          "degrees": 150
        },
        "swell": {
          "max": null
        },
        "tideState": "Run-in (approx)",
        "speciesTop": [
          "Tailor",
          "Flathead",
          "Bream"
        ]
      },
      {
        "date": "2026-02-11",
        "score": 3,
        "recommendation": "MAYBE",
        "wind": {
          "max": 16,
          "direction": "NE",
          "degrees": 33
        },
        "swell": {
          "max": null
        },
        "tideState": "Run-out (approx)",
        "speciesTop": [
          "Tailor",
          "Flathead",
          "Bream"
        ]
      },
      {
        "date": "2026-02-12",
        "score": 1,
        "recommendation": "GO TO PUB",
        "wind": {
          "max": 27,
          "direction": "S",
          "degrees": 176
        },
        "swell": {
          "max": null
        },
        "tideState": "Run-in (approx)",
        "speciesTop": [
          "Tailor",
          "Flathead",
          "Bream"
        ]
      },
      {
        "date": "2026-02-13",
        "score": 2,
        "recommendation": "GO TO PUB",
        "wind": {
          "max": 23,
          "direction": "SE",
          "degrees": 126
        },
        "swell": {
          "max": null
        },
        "tideState": "Run-out (approx)",
        "speciesTop": [
          "Tailor",
          "Flathead",
          "Bream"
        ]
      },
      {
        "date": "2026-02-14",
        "score": 3,
        "recommendation": "MAYBE",
        "wind": {
          "max": 17,
          "direction": "E",
          "degrees": 81
        },
        "swell": {
          "max": null
        },
        "tideState": "Run-in (approx)",
        "speciesTop": [
          "Tailor",
          "Flathead",
          "Bream"
        ]
      }
    ]
  },
  "redhead": {
    "name": "Redhead",
    "region": "Lake Macquarie",
    "updatedAt": "2026-02-08T06:49:49.682Z",
    "current": {
      "score": 3,
      "recommendation": "MAYBE",
      "bestTimes": [
        "Dawn",
        "Dusk"
      ],
      "species": [
        "Tailor",
        "Flathead",
        "Bream"
      ],
      "wind": {
        "speed": 4,
        "direction": "SE",
        "degrees": 143,
        "max": 18
      },
      "swell": {
        "height": null
      },
      "tide": {
        "state": "Run-in (approx)",
        "next": "Best bite ±2 hrs around tide change (approx)"
      }
    },
    "daily": [
      {
        "date": "2026-02-08",
        "score": 3,
        "recommendation": "MAYBE",
        "wind": {
          "max": 18,
          "direction": "S",
          "degrees": 169
        },
        "swell": {
          "max": null
        },
        "tideState": "Run-in (approx)",
        "speciesTop": [
          "Tailor",
          "Flathead",
          "Bream"
        ]
      },
      {
        "date": "2026-02-09",
        "score": 3,
        "recommendation": "MAYBE",
        "wind": {
          "max": 14,
          "direction": "N",
          "degrees": 5
        },
        "swell": {
          "max": null
        },
        "tideState": "Run-out (approx)",
        "speciesTop": [
          "Tailor",
          "Flathead",
          "Bream"
        ]
      },
      {
        "date": "2026-02-10",
        "score": 3,
        "recommendation": "MAYBE",
        "wind": {
          "max": 13,
          "direction": "SE",
          "degrees": 150
        },
        "swell": {
          "max": null
        },
        "tideState": "Run-in (approx)",
        "speciesTop": [
          "Tailor",
          "Flathead",
          "Bream"
        ]
      },
      {
        "date": "2026-02-11",
        "score": 3,
        "recommendation": "MAYBE",
        "wind": {
          "max": 16,
          "direction": "NE",
          "degrees": 33
        },
        "swell": {
          "max": null
        },
        "tideState": "Run-out (approx)",
        "speciesTop": [
          "Tailor",
          "Flathead",
          "Bream"
        ]
      },
      {
        "date": "2026-02-12",
        "score": 1,
        "recommendation": "GO TO PUB",
        "wind": {
          "max": 27,
          "direction": "S",
          "degrees": 176
        },
        "swell": {
          "max": null
        },
        "tideState": "Run-in (approx)",
        "speciesTop": [
          "Tailor",
          "Flathead",
          "Bream"
        ]
      },
      {
        "date": "2026-02-13",
        "score": 2,
        "recommendation": "GO TO PUB",
        "wind": {
          "max": 23,
          "direction": "SE",
          "degrees": 126
        },
        "swell": {
          "max": null
        },
        "tideState": "Run-out (approx)",
        "speciesTop": [
          "Tailor",
          "Flathead",
          "Bream"
        ]
      },
      {
        "date": "2026-02-14",
        "score": 3,
        "recommendation": "MAYBE",
        "wind": {
          "max": 17,
          "direction": "E",
          "degrees": 81
        },
        "swell": {
          "max": null
        },
        "tideState": "Run-in (approx)",
        "speciesTop": [
          "Tailor",
          "Flathead",
          "Bream"
        ]
      }
    ]
  },
  "terrigerl": {
    "name": "Terrigal",
    "region": "Central Coast",
    "updatedAt": "2026-02-08T06:49:49.682Z",
    "current": {
      "score": 3,
      "recommendation": "MAYBE",
      "bestTimes": [
        "Dawn",
        "Dusk"
      ],
      "species": [
        "Tailor",
        "Flathead",
        "Bream"
      ],
      "wind": {
        "speed": 3,
        "direction": "S",
        "degrees": 187,
        "max": 17
      },
      "swell": {
        "height": null
      },
      "tide": {
        "state": "Run-in (approx)",
        "next": "Best bite ±2 hrs around tide change (approx)"
      }
    },
    "daily": [
      {
        "date": "2026-02-08",
        "score": 3,
        "recommendation": "MAYBE",
        "wind": {
          "max": 17,
          "direction": "S",
          "degrees": 160
        },
        "swell": {
          "max": null
        },
        "tideState": "Run-in (approx)",
        "speciesTop": [
          "Tailor",
          "Flathead",
          "Bream"
        ]
      },
      {
        "date": "2026-02-09",
        "score": 4,
        "recommendation": "SEND IT",
        "wind": {
          "max": 10,
          "direction": "N",
          "degrees": 12
        },
        "swell": {
          "max": null
        },
        "tideState": "Run-out (approx)",
        "speciesTop": [
          "Tailor",
          "Bream",
          "Flathead"
        ]
      },
      {
        "date": "2026-02-10",
        "score": 4,
        "recommendation": "SEND IT",
        "wind": {
          "max": 11,
          "direction": "SE",
          "degrees": 147
        },
        "swell": {
          "max": null
        },
        "tideState": "Run-in (approx)",
        "speciesTop": [
          "Tailor",
          "Bream",
          "Flathead"
        ]
      },
      {
        "date": "2026-02-11",
        "score": 3,
        "recommendation": "MAYBE",
        "wind": {
          "max": 12,
          "direction": "NE",
          "degrees": 40
        },
        "swell": {
          "max": null
        },
        "tideState": "Run-out (approx)",
        "speciesTop": [
          "Tailor",
          "Bream",
          "Flathead"
        ]
      },
      {
        "date": "2026-02-12",
        "score": 2,
        "recommendation": "GO TO PUB",
        "wind": {
          "max": 24,
          "direction": "S",
          "degrees": 161
        },
        "swell": {
          "max": null
        },
        "tideState": "Run-in (approx)",
        "speciesTop": [
          "Tailor",
          "Flathead",
          "Bream"
        ]
      },
      {
        "date": "2026-02-13",
        "score": 3,
        "recommendation": "MAYBE",
        "wind": {
          "max": 18,
          "direction": "SE",
          "degrees": 126
        },
        "swell": {
          "max": null
        },
        "tideState": "Run-out (approx)",
        "speciesTop": [
          "Tailor",
          "Flathead",
          "Bream"
        ]
      },
      {
        "date": "2026-02-14",
        "score": 3,
        "recommendation": "MAYBE",
        "wind": {
          "max": 17,
          "direction": "E",
          "degrees": 73
        },
        "swell": {
          "max": null
        },
        "tideState": "Run-in (approx)",
        "speciesTop": [
          "Tailor",
          "Flathead",
          "Bream"
        ]
      }
    ]
  },
  "avoca": {
    "name": "Avoca Beach",
    "region": "Central Coast",
    "updatedAt": "2026-02-08T06:49:49.682Z",
    "current": {
      "score": 3,
      "recommendation": "MAYBE",
      "bestTimes": [
        "Dawn",
        "Dusk"
      ],
      "species": [
        "Tailor",
        "Flathead",
        "Bream"
      ],
      "wind": {
        "speed": 4,
        "direction": "SW",
        "degrees": 222,
        "max": 15
      },
      "swell": {
        "height": null
      },
      "tide": {
        "state": "Run-in (approx)",
        "next": "Best bite ±2 hrs around tide change (approx)"
      }
    },
    "daily": [
      {
        "date": "2026-02-08",
        "score": 3,
        "recommendation": "MAYBE",
        "wind": {
          "max": 15,
          "direction": "SE",
          "degrees": 144
        },
        "swell": {
          "max": null
        },
        "tideState": "Run-in (approx)",
        "speciesTop": [
          "Tailor",
          "Flathead",
          "Bream"
        ]
      },
      {
        "date": "2026-02-09",
        "score": 4,
        "recommendation": "SEND IT",
        "wind": {
          "max": 8,
          "direction": "N",
          "degrees": 347
        },
        "swell": {
          "max": null
        },
        "tideState": "Run-out (approx)",
        "speciesTop": [
          "Bream",
          "Tailor",
          "Flathead"
        ]
      },
      {
        "date": "2026-02-10",
        "score": 4,
        "recommendation": "SEND IT",
        "wind": {
          "max": 12,
          "direction": "E",
          "degrees": 102
        },
        "swell": {
          "max": null
        },
        "tideState": "Run-in (approx)",
        "speciesTop": [
          "Tailor",
          "Bream",
          "Flathead"
        ]
      },
      {
        "date": "2026-02-11",
        "score": 3,
        "recommendation": "MAYBE",
        "wind": {
          "max": 13,
          "direction": "NE",
          "degrees": 28
        },
        "swell": {
          "max": null
        },
        "tideState": "Run-out (approx)",
        "speciesTop": [
          "Tailor",
          "Bream",
          "Flathead"
        ]
      },
      {
        "date": "2026-02-12",
        "score": 1,
        "recommendation": "GO TO PUB",
        "wind": {
          "max": 29,
          "direction": "SE",
          "degrees": 157
        },
        "swell": {
          "max": null
        },
        "tideState": "Run-in (approx)",
        "speciesTop": [
          "Tailor",
          "Flathead",
          "Bream"
        ]
      },
      {
        "date": "2026-02-13",
        "score": 3,
        "recommendation": "MAYBE",
        "wind": {
          "max": 13,
          "direction": "SE",
          "degrees": 127
        },
        "swell": {
          "max": null
        },
        "tideState": "Run-out (approx)",
        "speciesTop": [
          "Tailor",
          "Flathead",
          "Bream"
        ]
      },
      {
        "date": "2026-02-14",
        "score": 3,
        "recommendation": "MAYBE",
        "wind": {
          "max": 17,
          "direction": "E",
          "degrees": 75
        },
        "swell": {
          "max": null
        },
        "tideState": "Run-in (approx)",
        "speciesTop": [
          "Tailor",
          "Flathead",
          "Bream"
        ]
      }
    ]
  },
  "the_entrance": {
    "name": "The Entrance",
    "region": "Central Coast",
    "updatedAt": "2026-02-08T06:49:49.682Z",
    "current": {
      "score": 3,
      "recommendation": "MAYBE",
      "bestTimes": [
        "Dawn",
        "Dusk"
      ],
      "species": [
        "Tailor",
        "Flathead",
        "Bream"
      ],
      "wind": {
        "speed": 3,
        "direction": "S",
        "degrees": 187,
        "max": 17
      },
      "swell": {
        "height": null
      },
      "tide": {
        "state": "Run-in (approx)",
        "next": "Best bite ±2 hrs around tide change (approx)"
      }
    },
    "daily": [
      {
        "date": "2026-02-08",
        "score": 3,
        "recommendation": "MAYBE",
        "wind": {
          "max": 17,
          "direction": "S",
          "degrees": 160
        },
        "swell": {
          "max": null
        },
        "tideState": "Run-in (approx)",
        "speciesTop": [
          "Tailor",
          "Flathead",
          "Bream"
        ]
      },
      {
        "date": "2026-02-09",
        "score": 4,
        "recommendation": "SEND IT",
        "wind": {
          "max": 10,
          "direction": "N",
          "degrees": 12
        },
        "swell": {
          "max": null
        },
        "tideState": "Run-out (approx)",
        "speciesTop": [
          "Tailor",
          "Bream",
          "Flathead"
        ]
      },
      {
        "date": "2026-02-10",
        "score": 4,
        "recommendation": "SEND IT",
        "wind": {
          "max": 11,
          "direction": "SE",
          "degrees": 147
        },
        "swell": {
          "max": null
        },
        "tideState": "Run-in (approx)",
        "speciesTop": [
          "Tailor",
          "Bream",
          "Flathead"
        ]
      },
      {
        "date": "2026-02-11",
        "score": 3,
        "recommendation": "MAYBE",
        "wind": {
          "max": 12,
          "direction": "NE",
          "degrees": 40
        },
        "swell": {
          "max": null
        },
        "tideState": "Run-out (approx)",
        "speciesTop": [
          "Tailor",
          "Bream",
          "Flathead"
        ]
      },
      {
        "date": "2026-02-12",
        "score": 2,
        "recommendation": "GO TO PUB",
        "wind": {
          "max": 24,
          "direction": "S",
          "degrees": 161
        },
        "swell": {
          "max": null
        },
        "tideState": "Run-in (approx)",
        "speciesTop": [
          "Tailor",
          "Flathead",
          "Bream"
        ]
      },
      {
        "date": "2026-02-13",
        "score": 3,
        "recommendation": "MAYBE",
        "wind": {
          "max": 18,
          "direction": "SE",
          "degrees": 126
        },
        "swell": {
          "max": null
        },
        "tideState": "Run-out (approx)",
        "speciesTop": [
          "Tailor",
          "Flathead",
          "Bream"
        ]
      },
      {
        "date": "2026-02-14",
        "score": 3,
        "recommendation": "MAYBE",
        "wind": {
          "max": 17,
          "direction": "E",
          "degrees": 73
        },
        "swell": {
          "max": null
        },
        "tideState": "Run-in (approx)",
        "speciesTop": [
          "Tailor",
          "Flathead",
          "Bream"
        ]
      }
    ]
  }
}